swarm_regulator/__init__.py
swarm_regulator/consumer.py
swarm_regulator/consumer_test.py
swarm_regulator/event_types/__init__.py
swarm_regulator/event_types/service.py
swarm_regulator/event_types/service_test.py
swarm_regulator/fixtures/service.json
swarm_regulator/logger.py
swarm_regulator-0.2.3.dist-info/WHEEL
swarm_regulator-0.2.3.dist-info/METADATA
swarm_regulator-0.2.3.dist-info/RECORD
