Metadata-Version: 2.1
Name: swarm-regulator
Version: 0.2.3
Summary: The regulator of your Docker Swarm cluster
License: MIT
Author: Paris Kasidiaris
Author-email: paris@sourcelair.com
Requires-Python: >=3.8,<4.0
Classifier: License :: OSI Approved :: MIT License
Classifier: Programming Language :: Python :: 3
Classifier: Programming Language :: Python :: 3.8
Requires-Dist: aiodocker (>=0.17.0,<0.18.0)
Requires-Dist: pytest-asyncio (>=0.10.0,<0.11.0)
